{
  "_comment": "MOCK of SOURCE 1: the smart contract (on-chain state). This is the data the frontend will later read via ethers.js — campaign financials + milestone release state + validator attestations. Joined with projectMetadata.json by id (campaigns), index (milestones) and address (validators).",
  "campaigns": [
    {
      "id": "burger-restaurant",
      "address": "0x7f4b2c9d1e3a5f7c8b0d2e4a6c8f1b3d5e7089a2",
      "currency": "USDC",
      "verified": true,
      "status": "laufend",
      "raised": 47520,
      "goal": 66000,
      "donors": 18,
      "daysLeft": 11,
      "timeLeftShort": "11d, 6 Std.",
      "milestones": [
        { "index": "01", "allocated": 12000, "status": "completed", "confirmations": 3, "totalValidators": 3 },
        { "index": "02", "allocated": 24000, "status": "completed", "confirmations": 3, "totalValidators": 3 },
        { "index": "03", "allocated": 18000, "status": "in_progress", "confirmations": 1, "totalValidators": 3 },
        { "index": "04", "allocated": 12000, "status": "pending", "confirmations": 0, "totalValidators": 3 }
      ],
      "validators": [
        { "address": "0x12b...c34", "uptime": 99.2 },
        { "address": "0x88f...e10", "uptime": 100 },
        { "address": "0x55a...d91", "uptime": 96.5 }
      ]
    },
    {
      "id": "mesh-netzwerk-festivals",
      "address": "0x3a1d8c2b4e6f0a9c7b5d3e1f8a06c4b2d9e177be",
      "currency": "USDC",
      "verified": true,
      "status": "laufend",
      "raised": 8100,
      "goal": 15000,
      "donors": 12,
      "daysLeft": 6,
      "timeLeftShort": "6d, 3 Std.",
      "milestones": [
        { "index": "01", "allocated": 6000, "status": "completed", "confirmations": 3, "totalValidators": 3 },
        { "index": "02", "allocated": 5000, "status": "in_progress", "confirmations": 2, "totalValidators": 3 },
        { "index": "03", "allocated": 4000, "status": "pending", "confirmations": 0, "totalValidators": 3 }
      ],
      "validators": [
        { "address": "0x12b...c34", "uptime": 99.2 },
        { "address": "0x88f...e10", "uptime": 100 },
        { "address": "0x55a...d91", "uptime": 96.5 }
      ]
    },
    {
      "id": "roguelike-aetherbound",
      "address": "0x9c2e7b4d1a8f3c6b0d5e9a2f7c1b8d6e304541af",
      "currency": "USDC",
      "verified": true,
      "status": "abgelaufen",
      "raised": 40000,
      "goal": 40000,
      "donors": 64,
      "daysLeft": 0,
      "timeLeftShort": "Beendet",
      "milestones": [
        { "index": "01", "allocated": 10000, "status": "completed", "confirmations": 3, "totalValidators": 3 },
        { "index": "02", "allocated": 15000, "status": "completed", "confirmations": 3, "totalValidators": 3 },
        { "index": "03", "allocated": 15000, "status": "completed", "confirmations": 3, "totalValidators": 3 }
      ],
      "validators": [
        { "address": "0x12b...c34", "uptime": 99.2 },
        { "address": "0x88f...e10", "uptime": 100 },
        { "address": "0x55a...d91", "uptime": 96.5 }
      ]
    },
    {
      "id": "mobile-suppenkueche-berlin",
      "address": "0x4d8f1a3c5e7b9d0a2c4e6f8b1d3a5c7e9f040b73",
      "currency": "USDC",
      "verified": true,
      "status": "laufend",
      "raised": 5460,
      "goal": 6000,
      "donors": 41,
      "daysLeft": 10,
      "timeLeftShort": "10d, 0 Std.",
      "milestones": [
        { "index": "01", "allocated": 3500, "status": "completed", "confirmations": 3, "totalValidators": 3 },
        { "index": "02", "allocated": 1500, "status": "in_progress", "confirmations": 2, "totalValidators": 3 },
        { "index": "03", "allocated": 1000, "status": "pending", "confirmations": 0, "totalValidators": 3 }
      ],
      "validators": [
        { "address": "0x12b...c34", "uptime": 99.2 },
        { "address": "0x88f...e10", "uptime": 100 },
        { "address": "0x55a...d91", "uptime": 96.5 }
      ]
    },
    {
      "id": "wiederaufforstung-eifel",
      "address": "0x6e0b4d6f8a0c2e4b6d8f0a2c4e6b8d0f2a46a2c5",
      "currency": "USDC",
      "verified": true,
      "status": "laufend",
      "raised": 6900,
      "goal": 30000,
      "donors": 27,
      "daysLeft": 18,
      "timeLeftShort": "18d, 7 Std.",
      "milestones": [
        { "index": "01", "allocated": 8000, "status": "completed", "confirmations": 3, "totalValidators": 3 },
        { "index": "02", "allocated": 12000, "status": "in_progress", "confirmations": 1, "totalValidators": 3 },
        { "index": "03", "allocated": 10000, "status": "pending", "confirmations": 0, "totalValidators": 3 }
      ],
      "validators": [
        { "address": "0x12b...c34", "uptime": 99.2 },
        { "address": "0x88f...e10", "uptime": 100 },
        { "address": "0x55a...d91", "uptime": 96.5 }
      ]
    }
  ]
}
